fathomdata/__init__.py
fathomdata/control_chart.py
fathomdata/document.py
fathomdata/fathom_api.py
fathomdata/sample_data.py
fathomdata/western_electric_rules.py
fathomdata-0.0.8.dist-info/METADATA
fathomdata-0.0.8.dist-info/WHEEL
fathomdata-0.0.8.dist-info/top_level.txt
fathomdata-0.0.8.dist-info/RECORD
