Metadata-Version: 2.1
Name: fathomdata
Version: 0.0.8
Summary: Python package to make interacting with life sciences manufacturing data quick and intuitive.
Home-page: UNKNOWN
Author: Fathom Data
License: UNKNOWN
Platform: UNKNOWN
Classifier: Programming Language :: Python :: 3
Classifier: Operating System :: OS Independent
Requires-Python: >=3.6
Requires-Dist: requests (>=2.22.0)
Requires-Dist: pandas (>=1.1.0)
Requires-Dist: bokeh (>=2.3.2)
Requires-Dist: python-dateutil (>=2.8.1)
